{
    "restaurants":[
        {
            "restaruranstTitle": "BBQ",
            "restaruranstImg": "https://blog.kakaocdn.net/dn/bYxk8F/btqzbVdZXnU/eDGWNmlponKBAabI83n5K0/img.jpg"
        },
        {
            "restaruranstTitle": "BHC",
            "restaruranstImg": "https://img.hankyung.com/photo/202102/01.25385808.1.jpg"
        },
        {
            "restaruranstTitle": "교촌",
            "restaruranstImg": "https://blog.kakaocdn.net/dn/Oa7Q7/btqJKwbjSi6/SINqMFkvDIzddiSlGTbcO0/img.jpg"
        },
        {
            "restaruranstTitle": "네네",
            "restaruranstImg": "https://blog.kakaocdn.net/dn/exLM42/btqwP7n6Me6/m2gfQtrk82t7iFVZkMLLH0/img.jpg"
        },
        {
            "restaruranstImg": "https://blog.kakaocdn.net/dn/bYxk8F/btqzbVdZXnU/eDGWNmlponKBAabI83n5K0/img.jpg"
        },
        {
            "restaruranstTitle": "자담",
            "restaruranstImg": "https://dnvefa72aowie.cloudfront.net/capri/smb/202010/632bb099466786b7168fbd1c2d8ec800005f8521cae4858b14.jpeg?q=95&s=1440x1440&t=inside"
        },
        {
            "restaruranstTitle": "처갓집",
            "restaruranstImg": "https://modo-phinf.pstatic.net/20190313_12/1552450405996Sl30x_JPEG/mosab6nNjN.jpeg?type=w1100"
        },
        {
            "restaruranstTitle": "호식이 두마리",
            "restaruranstImg": "https://encrypted-tbn0.gstatic.com/images?q=tbn:ANd9GcQgZAKasPf5QEY6QOJwUHhjDG19VtUM-Vz6E8kqqW2CNQdoLbia3orbpy5k7MpGoPaOvcw&usqp=CAU"
        }
    ]
}